Metadata-Version: 2.1
Name: odoo14-addon-delivery_roulier
Version: 14.0.1.1.0
Summary: Integration of multiple carriers
Home-page: https://github.com/OCA/delivery-carrier
Author: Akretion,Odoo Community Association (OCA)
Author-email: support@odoo-community.org
License: AGPL-3
Classifier: Programming Language :: Python
Classifier: Framework :: Odoo
Classifier: Framework :: Odoo :: 14.0
Classifier: License :: OSI Approved :: GNU Affero General Public License v3
Requires-Python: >=3.6
Requires-Dist: odoo14-addon-base-delivery-carrier-label
Requires-Dist: odoo14-addon-base-phone
Requires-Dist: odoo14-addon-partner-helper
Requires-Dist: odoo <14.1dev,>=14.0a
Requires-Dist: roulier
